cerespp/__init__.py
cerespp/__main__.py
cerespp/cerespp.py
cerespp/constants.py
cerespp/cpplots.py
cerespp/crosscorr.py
cerespp/logger.py
cerespp/models.py
cerespp/processor.py
cerespp/spectra_utils.py
cerespp/utils.py
cerespp/masks/G2.mas
cerespp/masks/K0.mas
cerespp/masks/K5.mas
cerespp/masks/M2.mas
cerespp-1.3.4.dist-info/licenses/LICENSE
tests/__init__.py
tests/test_cli.py
tests/test_imports.py
tests/test_logger.py
tests/test_models.py
tests/test_processor.py
cerespp-1.3.4.dist-info/METADATA
cerespp-1.3.4.dist-info/WHEEL
cerespp-1.3.4.dist-info/entry_points.txt
cerespp-1.3.4.dist-info/top_level.txt
cerespp-1.3.4.dist-info/RECORD
