Metadata-Version: 2.4
Name: cerespp
Version: 1.3.4
Summary: An extension to ceres.
Home-page: https://github.com/jvines/Ceres-plusplus
Author: Jose Vines
Author-email: jose.vines@ug.uchile.cl
Maintainer: Jose Vines
Maintainer-email: jose.vines@ug.uchile.cl
License: MIT
Classifier: Development Status :: 4 - Beta
Classifier: Programming Language :: Python :: 3
Classifier: Intended Audience :: Science/Research
Classifier: License :: OSI Approved :: MIT License
Classifier: Operating System :: OS Independent
Classifier: Topic :: Scientific/Engineering :: Astronomy
Requires-Python: >=3.6
License-File: LICENSE
Requires-Dist: numpy
Requires-Dist: scipy
Requires-Dist: matplotlib
Requires-Dist: astropy
Requires-Dist: PyAstronomy
Requires-Dist: tqdm
Requires-Dist: termcolor
Dynamic: author
Dynamic: author-email
Dynamic: classifier
Dynamic: description
Dynamic: description-content-type
Dynamic: home-page
Dynamic: license
Dynamic: license-file
Dynamic: maintainer
Dynamic: maintainer-email
Dynamic: requires-dist
Dynamic: requires-python
Dynamic: summary
